README.rst
setup.cfg
setup.py
./__init__.py
./model.py
./tryton.cfg
./urls.xml
./templates/registration.jinja
./templates/tests/from-module.html
./templates/tests/test-changing-context.html
./templates/tests/translation-test.html
trytond_nereid_test.egg-info/PKG-INFO
trytond_nereid_test.egg-info/SOURCES.txt
trytond_nereid_test.egg-info/dependency_links.txt
trytond_nereid_test.egg-info/entry_points.txt
trytond_nereid_test.egg-info/not-zip-safe
trytond_nereid_test.egg-info/requires.txt
trytond_nereid_test.egg-info/top_level.txt